ikup/__init__.py
ikup/cli.py
ikup/graphics_command.py
ikup/graphics_terminal.py
ikup/id_manager.py
ikup/ikup_terminal.py
ikup/placeholder.py
ikup/terminal_detection.py
ikup/utils.py
ikup/testing/__init__.py
ikup/testing/cli.py
ikup/testing/comparison.py
ikup/testing/context.py
ikup/testing/output_comparison.py
ikup/testing/test_basics.py
ikup/testing/test_deletion.py
ikup/testing/test_ikup_terminal.py
ikup/testing/test_placeholder.py
ikup/testing/test_placement.py
ikup/testing/test_response.py
ikup/testing/test_uploading.py
ikup-0.1.0.dist-info/METADATA
ikup-0.1.0.dist-info/WHEEL
ikup-0.1.0.dist-info/entry_points.txt
ikup-0.1.0.dist-info/RECORD
