Metadata-Version: 2.4
Name: ikup
Version: 0.1.0
Summary: A tool for displaying images in the terminal using the kitty graphics protocol.
Requires-Python: >=3.10
Requires-Dist: pillow
Requires-Dist: platformdirs
Requires-Dist: psutil
Requires-Dist: toml
Provides-Extra: test
Requires-Dist: numpy; extra == 'test'
Requires-Dist: pytest; extra == 'test'
